<dialogue type="onDemand" ntargets="1" id="demandQuest">
        <text id="0">So...</text>
        <text id="1">You are the new officer in charge of the population census, right?</text>
        <text id="2">Very well. Let's see... Here is your notebook. Try to open it.</text>
        <!--Faire apparaitre le bouton du carnet et laisser le joueur l'ouvrir et le fermer-->
        <text id="3" objectif="0" replay="2">It is supposed to contain important information on</text>
        <text id="4">the inhabitants of Lausanne,</text>
        <text id="5">but as you probably noticed,</text>
        <text id="6">some information is missing.</text>
        <text id="7">Try to complete the first page.</text>
        <text id="8">You can ask my colleague, I think she knows this person</text>
        <text id="9">and I believe we have a letter addressed to her on the desk.</text>
        <!--Faire apparaitre le NPC et l'item et laisser le joueur remplir la première page-->
        <text id="10" objectif="2" replay="7">Well done! You completed the first page.</text>
        <text id="11">Now, there are 5 more pages to fill.</text>
        <text id="12">Take this map.</text>
        <text id="13">Try to find all the missing information around town</text>
        <text id="14">and come back once you have completed the notebook.</text>
        <!--Ensuite dialogue qui se trouve dans NPC.cs-->
        <text id="15" signal="EndQuest"></text>
</dialogue>